markus_exam_matcher/__init__.py
markus_exam_matcher/__main__.py
markus_exam_matcher/_cnn/__init__.py
markus_exam_matcher/_cnn/cnn.py
markus_exam_matcher/_cnn/emnist_cnn.pt
markus_exam_matcher/_cnn/model_numeric_epoch_24.pth
markus_exam_matcher/core/__init__.py
markus_exam_matcher/core/char_types.py
markus_exam_matcher/core/display_elements.py
markus_exam_matcher/image_processing/__init__.py
markus_exam_matcher/image_processing/box_detection.py
markus_exam_matcher/image_processing/image_transformation_pipelines.py
markus_exam_matcher/image_processing/image_transformations.py
markus_exam_matcher/image_processing/read_chars.py
markus_exam_matcher/qr_scan/__init__.py
markus_exam_matcher/qr_scan/scan_qr.py
markus_exam_matcher-0.3.0.dist-info/licenses/LICENSE
markus_exam_matcher-0.3.0.dist-info/WHEEL
markus_exam_matcher-0.3.0.dist-info/METADATA
markus_exam_matcher-0.3.0.dist-info/RECORD
