Metadata-Version: 2.4
Name: markus-exam-matcher
Version: 0.3.0
Summary: A package for matching students to test papers in MarkUs
Author: Hannah Li, Anis Singh
Author-email: Hannah Li <hannah.li97@gmail.com>, Anis Singh <anisnylesingh@gmail.com>
License-Expression: MIT
License-File: LICENSE
Classifier: Programming Language :: Python :: 3
Classifier: License :: OSI Approved :: MIT License
Classifier: Operating System :: OS Independent
Requires-Dist: numpy>=2.0.0,<2.5
Requires-Dist: opencv-python-headless==4.12.0.88
Requires-Dist: pdf2image==1.17.0
Requires-Dist: pillow==12.0.0
Requires-Dist: scipy==1.16.3
Requires-Dist: torch==2.9.1
Requires-Dist: torchvision==0.24.1
Requires-Dist: zxing-cpp==2.3.0
Maintainer: David Liu
Maintainer-email: David Liu <david@cs.toronto.edu>
Requires-Python: >=3.11, <3.15
Project-URL: Bug Tracker, https://github.com/MarkUsProject/markus-exam-matcher/issues
Project-URL: Homepage, https://github.com/MarkUsProject/markus-exam-matcher
